{
  "editor:rename-heading": [
    {
      "modifiers": [
        "Shift"
      ],
      "key": "F6"
    }
  ],
  "app:delete-file": [
    {
      "modifiers": [
        "Mod"
      ],
      "key": "Delete"
    }
  ],
  "workspace:export-pdf": [
    {
      "modifiers": [
        "Mod"
      ],
      "key": "P"
    }
  ],
  "command-palette:open": [],
  "app:toggle-left-sidebar": [
    {
      "modifiers": [
        "Alt"
      ],
      "key": "1"
    }
  ],
  "app:toggle-right-sidebar": [
    {
      "modifiers": [
        "Alt"
      ],
      "key": "2"
    }
  ],
  "app:open-vault": [
    {
      "modifiers": [
        "Mod"
      ],
      "key": "O"
    }
  ],
  "workspace:new-tab": [],
  "insert-template": [
    {
      "modifiers": [
        "Alt",
        "Mod"
      ],
      "key": "Insert"
    }
  ],
  "editor:insert-link": [],
  "switcher:open": [
    {
      "modifiers": [
        "Mod",
        "Shift"
      ],
      "key": "N"
    }
  ],
  "file-explorer:new-file-in-new-pane": [],
  "open-with-default-app:show": [
    {
      "modifiers": [
        "Mod",
        "Shift"
      ],
      "key": "E"
    }
  ]
}